{
  "trigger": true,
  "modules": [
    "custom"
  ],
  "parentResource": "machinelearningapp",
  "functionName": "machinelearningappPreSignup",
  "resourceName": "machinelearningappPreSignup",
  "parentStack": "auth",
  "triggerEnvs": "[]",
  "triggerDir": "/snapshot/amplify-cli/build/node_modules/@aws-amplify/amplify-category-auth/provider-utils/awscloudformation/triggers/PreSignup",
  "triggerTemplate": "PreSignup.json.ejs",
  "triggerEventPath": "PreSignup.event.json",
  "roleName": "machinelearningappPreSignup",
  "skipEdit": true,
  "permissions": {
    "api": {
      "machinelearningapp": [
        "Mutation"
      ]
    }
  }
}